fwtp/FWTP.py
fwtp/StringIteratorIO.py
fwtp/__init__.py
fwtp-2.1.4.dist-info/METADATA
fwtp-2.1.4.dist-info/WHEEL
fwtp-2.1.4.dist-info/top_level.txt
fwtp-2.1.4.dist-info/RECORD
